.gitignore
CHANGES.txt
CONTRIBUTORS.txt
MANIFEST.in
README.rst
bootstrap.py
buildout.cfg
setup.cfg
setup.py
docs/LICENSE.GPL
docs/LICENSE.txt
src/edition1/__init__.py
src/edition1.twitterportletfix.egg-info/PKG-INFO
src/edition1.twitterportletfix.egg-info/SOURCES.txt
src/edition1.twitterportletfix.egg-info/dependency_links.txt
src/edition1.twitterportletfix.egg-info/entry_points.txt
src/edition1.twitterportletfix.egg-info/namespace_packages.txt
src/edition1.twitterportletfix.egg-info/not-zip-safe
src/edition1.twitterportletfix.egg-info/requires.txt
src/edition1.twitterportletfix.egg-info/top_level.txt
src/edition1/twitterportletfix/__init__.py
src/edition1/twitterportletfix/build_i18n.sh
src/edition1/twitterportletfix/configure.zcml
src/edition1/twitterportletfix/interfaces.py
src/edition1/twitterportletfix/permissions.zcml
src/edition1/twitterportletfix/testing.py
src/edition1/twitterportletfix/Extensions/__init__.py
src/edition1/twitterportletfix/Extensions/install.py
src/edition1/twitterportletfix/browser/__init__.py
src/edition1/twitterportletfix/browser/configure.zcml
src/edition1/twitterportletfix/browser/controlpanel.py
src/edition1/twitterportletfix/browser/icons/twitter.png
src/edition1/twitterportletfix/locales/edition1.twitterportletfix.pot
src/edition1/twitterportletfix/locales/en/LC_MESSAGES/edition1.twitterportletfix.po
src/edition1/twitterportletfix/locales/nl/LC_MESSAGES/edition1.twitterportletfix.po
src/edition1/twitterportletfix/portlets/__init__.py
src/edition1/twitterportletfix/portlets/configure.zcml
src/edition1/twitterportletfix/portlets/portlet.py
src/edition1/twitterportletfix/profiles/default/browserlayer.xml
src/edition1/twitterportletfix/profiles/default/controlpanel.xml
src/edition1/twitterportletfix/profiles/default/metadata.xml
src/edition1/twitterportletfix/profiles/default/registry.xml
src/edition1/twitterportletfix/profiles/default/rolemap.xml
src/edition1/twitterportletfix/profiles/uninstall/browserlayer.xml
src/edition1/twitterportletfix/profiles/uninstall/controlpanel.xml
src/edition1/twitterportletfix/profiles/uninstall/registry.xml
src/edition1/twitterportletfix/tests/__init__.py
src/edition1/twitterportletfix/tests/robot_test.txt
src/edition1/twitterportletfix/tests/test_example.py
src/edition1/twitterportletfix/tests/test_robot.py