Metadata-Version: 1.1
Name: edition1.twitterportletfix
Version: 1.0
Summary: Quick fix for collective.twitterportlet for Twitter API v1.1
Home-page: https://github.com/edition1/edition1.twitterportletfix
Author: Edition1
Author-email: info@edition1.nl
License: gpl
Keywords: Plone Twitter portlet
Platform: UNKNOWN
Classifier: Environment :: Web Environment
Classifier: Framework :: Plone :: 4.1
Classifier: Framework :: Plone :: 4.3
Classifier: Operating System :: OS Independent
Classifier: Programming Language :: Python
Classifier: Programming Language :: Python :: 2.6
Classifier: Programming Language :: Python :: 2.7
Classifier: Topic :: Software Development :: Libraries :: Python Modules
